AreaCalc/Area.py
AreaCalc/TestArea.py
AreaCalc/__init__.py
areacalc-0.0.1.dist-info/METADATA
areacalc-0.0.1.dist-info/WHEEL
areacalc-0.0.1.dist-info/top_level.txt
areacalc-0.0.1.dist-info/RECORD
