Metadata-Version: 2.1
Name: areacalc
Version: 0.0.1
Summary: This is the simple area calculator of different 2d figures.
Author: k1zon
Project-URL: GitHub, https://github.com/K1Zon/AreaCalc_Lib
Keywords: areacalc
Classifier: Programming Language :: Python :: 3.11
Requires-Python: >=3.6
